api_bricks_sec_api_rest/__init__.py
api_bricks_sec_api_rest/api_client.py
api_bricks_sec_api_rest/api_response.py
api_bricks_sec_api_rest/configuration.py
api_bricks_sec_api_rest/exceptions.py
api_bricks_sec_api_rest/rest.py
api_bricks_sec_api_rest/api/__init__.py
api_bricks_sec_api_rest/api/content_extraction_api.py
api_bricks_sec_api_rest/api/filing_metadata_api.py
api_bricks_sec_api_rest/api/full_text_search_api.py
api_bricks_sec_api_rest/api/xbrl_conversion_api.py
api_bricks_sec_api_rest/models/__init__.py
api_bricks_sec_api_rest/models/dto_extractor_type.py
api_bricks_sec_api_rest/models/dto_filing_metadata_dto.py
api_bricks_sec_api_rest/models/dto_filing_sort_by.py
api_bricks_sec_api_rest/models/dto_sec_filing_result_dto.py
api_bricks_sec_api_rest/models/mvc_problem_details.py
api_bricks_sec_api_rest/models/mvc_validation_problem_details.py
api_bricks_sec_api_rest/test/__init__.py
api_bricks_sec_api_rest/test/test_content_extraction_api.py
api_bricks_sec_api_rest/test/test_dto_extractor_type.py
api_bricks_sec_api_rest/test/test_dto_filing_metadata_dto.py
api_bricks_sec_api_rest/test/test_dto_filing_sort_by.py
api_bricks_sec_api_rest/test/test_dto_sec_filing_result_dto.py
api_bricks_sec_api_rest/test/test_filing_metadata_api.py
api_bricks_sec_api_rest/test/test_full_text_search_api.py
api_bricks_sec_api_rest/test/test_mvc_problem_details.py
api_bricks_sec_api_rest/test/test_mvc_validation_problem_details.py
api_bricks_sec_api_rest/test/test_xbrl_conversion_api.py
api_bricks_sec_api_rest-1.0.2.dist-info/METADATA
api_bricks_sec_api_rest-1.0.2.dist-info/WHEEL
api_bricks_sec_api_rest-1.0.2.dist-info/top_level.txt
api_bricks_sec_api_rest-1.0.2.dist-info/RECORD
