Metadata-Version: 2.4
Name: api-bricks-sec-api-rest
Version: 1.0.2
Summary: SDKs for API BRICKS SEC API
Home-page: https://docs.finfeedapi.com/sec-api/
Author: Tomasz Przybysz
Author-email: tprzybysz@coinapi.io
Classifier: Programming Language :: Python :: 3
Classifier: License :: OSI Approved :: MIT License
Classifier: Operating System :: OS Independent
Requires-Python: >=3.0
Dynamic: author
Dynamic: author-email
Dynamic: classifier
Dynamic: description
Dynamic: description-content-type
Dynamic: home-page
Dynamic: requires-python
Dynamic: summary
